{"cameraMode":{"drawMode":0,"name":"Shaded","section":"Shading Mode"},"sceneLighting":true,"audioPlay":false,"sceneViewState":{"showFog":true,"showMaterialUpdate":false,"showSkybox":true,"showFlares":true,"showImageEffects":true,"showParticleSystems":true},"in2DMode":false,"pivot":{"x":-23.091487884521486,"y":8.871532440185547,"z":4.069735527038574},"rotation":{"x":0.001972320256754756,"y":0.9958330988883972,"z":-0.08957543969154358,"w":0.02203040011227131},"size":1.4866905212402344,"orthographic":false}